recent_state_summarizer/__init__.py
recent_state_summarizer/__main__.py
recent_state_summarizer/summarize.py
recent_state_summarizer/fetch/__init__.py
recent_state_summarizer/fetch/adventar.py
recent_state_summarizer/fetch/hatena_blog.py
recent_state_summarizer/fetch/hatena_bookmark.py
recent_state_summarizer/fetch/qiita_advent_calendar.py
recent_state_summarizer-0.0.8.dist-info/licenses/LICENSE
tests/fetch/__init__.py
tests/fetch/test_adventar.py
tests/fetch/test_core.py
tests/fetch/test_hatena_blog.py
tests/fetch/test_hatena_bookmark.py
tests/fetch/test_qiita_advent_calendar.py
recent_state_summarizer-0.0.8.dist-info/METADATA
recent_state_summarizer-0.0.8.dist-info/WHEEL
recent_state_summarizer-0.0.8.dist-info/entry_points.txt
recent_state_summarizer-0.0.8.dist-info/top_level.txt
recent_state_summarizer-0.0.8.dist-info/RECORD
