Metadata-Version: 2.4
Name: recent-state-summarizer
Version: 0.0.8
Summary: Summarize a list of entry titles using LLM
Author-email: nikkie <takuyafjp+develop@gmail.com>
License: MIT
Classifier: Development Status :: 1 - Planning
Classifier: License :: OSI Approved :: MIT License
Classifier: Programming Language :: Python
Classifier: Programming Language :: Python :: 3
Classifier: Programming Language :: Python :: 3.10
Classifier: Programming Language :: Python :: 3.11
Classifier: Programming Language :: Python :: 3.12
Classifier: Programming Language :: Python :: 3.13
Classifier: Programming Language :: Python :: 3.14
Requires-Python: >=3.10
License-File: LICENSE
Requires-Dist: beautifulsoup4
Requires-Dist: feedparser
Requires-Dist: httpx
Requires-Dist: openai<1
Provides-Extra: testing
Requires-Dist: pytest; extra == "testing"
Requires-Dist: responses; extra == "testing"
Requires-Dist: respx; extra == "testing"
Provides-Extra: lint
Requires-Dist: flake8; extra == "lint"
Requires-Dist: black; extra == "lint"
Requires-Dist: isort; extra == "lint"
Provides-Extra: dev
Requires-Dist: wheel; extra == "dev"
Requires-Dist: build; extra == "dev"
Requires-Dist: twine; extra == "dev"
Dynamic: license-file
